vnmrjpy/__init__.py
vnmrjpy/aloha/__init__.py
vnmrjpy/aloha/aloha.py
vnmrjpy/aloha/aloha_old.py
vnmrjpy/aloha/alternatingdmm.py
vnmrjpy/aloha/hankelutils.py
vnmrjpy/aloha/jitutils.py
vnmrjpy/aloha/lmafit.py
vnmrjpy/aloha/lowranksolvers.py
vnmrjpy/aloha/mathutils.py
vnmrjpy/aloha/pyramidal.py
vnmrjpy/aloha/singularvt.py
vnmrjpy/config/vnmrjpy.conf
vnmrjpy/core/__init__.py
vnmrjpy/core/epitools.py
vnmrjpy/core/fit.py
vnmrjpy/core/niftitools.py
vnmrjpy/core/read.py
vnmrjpy/core/recon.py
vnmrjpy/core/transform.py
vnmrjpy/core/utils.py
vnmrjpy/core/varray.py
vnmrjpy/core/write.py
vnmrjpy/fit/__init__.py
vnmrjpy/fit/ideal.py
vnmrjpy/fit/t2.py
vnmrjpy/func/__init__.py
vnmrjpy/func/base.py
vnmrjpy/func/composer.py
vnmrjpy/func/wasabi.py
vnmrjpy/io/__init__.py
vnmrjpy/io/readfdf.py
vnmrjpy/io/readfid.py
vnmrjpy/io/readnifti.py
vnmrjpy/io/readprocpar.py
vnmrjpy/io/saverecon.py
vnmrjpy/io/writefdf.py
vnmrjpy/io/writenifti.py
vnmrjpy/recon/__init__.py
vnmrjpy/recon/imake.py
vnmrjpy/recon/kfill.py
vnmrjpy/recon/kmake.py
vnmrjpy/recon/phasematch.py
vnmrjpy/scripts/fdf2nii
vnmrjpy/scripts/fid2nii
vnmrjpy/scripts/gskipint
vnmrjpy/scripts/niview
vnmrjpy/scripts/pyrecon
vnmrjpy/scripts/vjinfo
vnmrjpy/scripts/vnmrjpyconf
vnmrjpy/sge/__init__.py
vnmrjpy/sge/gridutils.py
vnmrjpy/util/__init__.py
vnmrjpy/util/configparser.py
vnmrjpy/util/csdatagen.py
vnmrjpy/util/csfiberfetch.py
vnmrjpy/util/cstestio.py
vnmrjpy/util/disgusting.py
vnmrjpy/util/fidutils.py
vnmrjpy/util/niftiutils.py
vnmrjpy/util/plotutils.py
vnmrjpy/util/readpetable.py
vnmrjpy/util/skipinttools.py
vnmrjpy/util/transform.py
vnmrjpy-0.1.dev3.data/scripts/fdf2nii
vnmrjpy-0.1.dev3.data/scripts/fid2nii
vnmrjpy-0.1.dev3.data/scripts/gskipint
vnmrjpy-0.1.dev3.data/scripts/niview
vnmrjpy-0.1.dev3.data/scripts/pyrecon
vnmrjpy-0.1.dev3.data/scripts/vjinfo
vnmrjpy-0.1.dev3.data/scripts/vnmrjpyconf
vnmrjpy-0.1.dev3.dist-info/LICENSE.txt
vnmrjpy-0.1.dev3.dist-info/METADATA
vnmrjpy-0.1.dev3.dist-info/WHEEL
vnmrjpy-0.1.dev3.dist-info/top_level.txt
vnmrjpy-0.1.dev3.dist-info/RECORD
