Metadata-Version: 2.1
Name: vnmrjpy
Version: 0.1.dev3
Summary: Handle VnmrJ MRI data and recostruction with Python
Home-page: https://github.com/hlatkydavid/vnmrjpy
Author: David Hlatky
Author-email: hlatkydavid@gmail.com
License: UNKNOWN
Platform: UNKNOWN
Requires-Python: >=3.5
Requires-Dist: lmfit
Requires-Dist: numpy
Requires-Dist: scipy
Requires-Dist: matplotlib
Requires-Dist: nibabel
